LICENSE
README.md
setup.py
./bcause/__init__.py
bcause/__init__.py
bcause.egg-info/PKG-INFO
bcause.egg-info/SOURCES.txt
bcause.egg-info/dependency_links.txt
bcause.egg-info/requires.txt
bcause.egg-info/top_level.txt
bcause/conversion/__init__.py
bcause/conversion/pgmpy.py
bcause/factors/__init__.py
bcause/factors/deterministic.py
bcause/factors/factor.py
bcause/factors/imprecise.py
bcause/factors/mulitnomial.py
bcause/factors/values/__init__.py
bcause/factors/values/btreeops.py
bcause/factors/values/btreestore.py
bcause/factors/values/listops.py
bcause/factors/values/liststore.py
bcause/factors/values/numpyops.py
bcause/factors/values/numpystore.py
bcause/factors/values/operations.py
bcause/factors/values/store.py
bcause/factors/values/treedictops.py
bcause/factors/values/treedictstore.py
bcause/inference/__init__.py
bcause/inference/inference.py
bcause/inference/ordering.py
bcause/inference/causal/__init__.py
bcause/inference/causal/causal.py
bcause/inference/causal/elimination.py
bcause/inference/causal/multi.py
bcause/inference/probabilistic/__init__.py
bcause/inference/probabilistic/datainference.py
bcause/inference/probabilistic/elimination.py
bcause/inference/probabilistic/probabilistic.py
bcause/learning/__init__.py
bcause/learning/aggregator/__init__.py
bcause/learning/aggregator/aggregator.py
bcause/learning/causal/__init__.py
bcause/learning/parameter/__init__.py
bcause/learning/parameter/expectation_maximization.py
bcause/learning/parameter/gradient.py
bcause/learning/parameter/parameter.py
bcause/models/__init__.py
bcause/models/bnet.py
bcause/models/cmodel.py
bcause/models/info.py
bcause/models/pgmodel.py
bcause/models/sampling.py
bcause/models/transform/__init__.py
bcause/models/transform/combination.py
bcause/models/transform/conversion.py
bcause/models/transform/simplification.py
bcause/readwrite/__init__.py
bcause/readwrite/bnread.py
bcause/readwrite/bnwrite.py
bcause/readwrite/scmread.py
bcause/readwrite/scmwrite.py
bcause/util/__init__.py
bcause/util/arrayutils.py
bcause/util/assertions.py
bcause/util/datadeps.py
bcause/util/datautils.py
bcause/util/domainutils.py
bcause/util/graphutils.py
