Metadata-Version: 2.1
Name: bcause
Version: 0.0.2
Summary: Causal reasoning with PGMs
Home-page: https://github.com/PGM-Lab/bcause
Author: Rafael Cabañas
Author-email: rcabanas@ual.es
License: Apache License 2.0
Platform: UNKNOWN
Classifier: Intended Audience :: Developers
Classifier: Intended Audience :: Education
Classifier: Intended Audience :: Science/Research
Classifier: License :: OSI Approved :: Apache Software License
Classifier: Operating System :: POSIX :: Linux
Classifier: Operating System :: MacOS :: MacOS X
Classifier: Operating System :: Microsoft :: Windows
Classifier: Programming Language :: Python :: 3.6
Requires-Python: >=3.6
License-File: LICENSE
